asyncrpc/__init__.py
asyncrpc/call.py
asyncrpc/cleaner.py
asyncrpc/client.py
asyncrpc/server.py
asyncrpc/utils.py
asyncrpc/tests/__init__.py
asyncrpc/tests/test_call.py
asyncrpc/tests/test_cleaner.py
asyncrpc/tests/test_server.py
asyncrpc-0.1.4.dist-info/DESCRIPTION.rst
asyncrpc-0.1.4.dist-info/METADATA
asyncrpc-0.1.4.dist-info/RECORD
asyncrpc-0.1.4.dist-info/WHEEL
asyncrpc-0.1.4.dist-info/metadata.json
asyncrpc-0.1.4.dist-info/top_level.txt
